{
    "quotes": [
        {
            "id": 1,
            "text": "Wubba Lubba Dub Dub!"
        },
        {
            "id": 2,
            "text": "...What People Call 'Love' Is Just A Chemical Reaction That Compels Animals To Breed. It Hits Hard, Morty, Then It Slowly Fades, Leaving You Stranded In A Failing Marriage."
        },
        {
            "id": 3,
            "text": "Because I Don't Respect Therapy. Because I'm A Scientist. Because I Invent, Transform, Create, And Destroy For A Living, And When I Don't Like Something About The World, I Change It."
        },
        {
            "id": 4,
            "text": "You Act Like Prey, But You're A Predator! You Use Pity To Lure In Your Victims! That's How You Survive!"
        },
        {
            "id": 5,
            "text": "The universe is basically an animal. It grazes on the ordinary. It creates infinite idiots just to eat them."
        },
        {
            "id": 6,
            "text": "To live is to risk it all; otherwise you’re just an inert chunk of randomly assembled molecules drifting wherever the universe blows you…"
        },
        {
            "id": 7,
            "text": "Sometimes Science Is More Art Than Science."
        },
        {
            "id": 8,
            "text": "You Still Have A Right To Take Anything You Want Seriously."
        },
        {
            "id": 9,
            "text": "YWeddings Are Basically Funerals With Cake."
        },
        {
            "id": 10,
            "text": "If I Wanted To Be Sober, I Wouldn't Have Gotten Drunk."
        },
        {
            "id": 11,
            "text": "If You Spend All Day Shuffling Words Around, You Can Make Anything Sound Bad, Morty."
        }
    ]
}